setup.py
MQprobability/Binomialdistribution.py
MQprobability/Gaussiandistribution.py
MQprobability/Generaldistribution.py
MQprobability/__init__.py
MQprobability.egg-info/PKG-INFO
MQprobability.egg-info/SOURCES.txt
MQprobability.egg-info/dependency_links.txt
MQprobability.egg-info/not-zip-safe
MQprobability.egg-info/top_level.txt