Metadata-Version: 1.0
Name: MQprobability
Version: 1.0
Summary: Gaussian and Binomial distributions
Home-page: UNKNOWN
Author: Max Qiu
Author-email: UNKNOWN
License: UNKNOWN
Platform: UNKNOWN
